.DS_Store
cli/__init__.py
cli/constants.py
cli/main.py
cli/approximate_cost/__init__.py
cli/approximate_cost/cost.py
cli/cost/__init__.py
cli/cost/embeddings.py
cli/cost/input.py
cli/cost/output.py
cli/doc/doc.md
cli/evals/__init__.py
cli/evals/classification.py
cli/evals/code_generation.py
cli/evals/elovalue.py
cli/evals/equals.py
cli/evals/function_calling.py
cli/evals/includes.py
cli/evals/json_validation.py
cli/evals/semantic_similarity.py
cli/openai_calls/__init__.py
cli/openai_calls/openai_call.py
cli/prompt_generation/__init__.py
cli/prompt_generation/generation.py
cli/prompt_generation/iteration.py
cli/validation_yaml/__init__.py
cli/validation_yaml/validation.py
promptwizard/__init__.py
promptwizard/constants.py
promptwizard/main.py
promptwizard/approximate_cost/__init__.py
promptwizard/approximate_cost/cost.py
promptwizard/cost/__init__.py
promptwizard/cost/embeddings.py
promptwizard/cost/input.py
promptwizard/cost/output.py
promptwizard/doc/doc.md
promptwizard/evals/__init__.py
promptwizard/evals/classification.py
promptwizard/evals/code_generation.py
promptwizard/evals/elovalue.py
promptwizard/evals/equals.py
promptwizard/evals/function_calling.py
promptwizard/evals/includes.py
promptwizard/evals/json_validation.py
promptwizard/evals/semantic_similarity.py
promptwizard/openai_calls/__init__.py
promptwizard/openai_calls/openai_call.py
promptwizard/prompt_generation/__init__.py
promptwizard/prompt_generation/generation.py
promptwizard/prompt_generation/iteration.py
promptwizard/validation_yaml/__init__.py
promptwizard/validation_yaml/validation.py
promptwizard-0.0.0.dist-info/LICENSE
promptwizard-0.0.0.dist-info/METADATA
promptwizard-0.0.0.dist-info/WHEEL
promptwizard-0.0.0.dist-info/entry_points.txt
promptwizard-0.0.0.dist-info/top_level.txt
promptwizard-0.0.0.dist-info/RECORD
