Metadata-Version: 2.1
Name: promptwizard
Version: 0.0.0
Summary: Prompt Wizard is a package for evaluating custom prompts using various evaluation methods. It allows you to provide your own prompts or generate them automatically and then obtain the results in a JSON file.
License: MIT
Requires-Python: >=3.8
License-File: LICENSE
Requires-Dist: openai (>=0.27.0)
Requires-Dist: PyYAML (>=5.4)
Requires-Dist: matplotlib
Requires-Dist: numpy
Requires-Dist: marshmallow
Requires-Dist: tiktoken (>=0.4.0)
Requires-Dist: tenacity
Requires-Dist: zipp
Requires-Dist: six
Requires-Dist: aiohttp
Requires-Dist: urllib3
Requires-Dist: certifi
Requires-Dist: tqdm
Requires-Dist: python-dotenv
Requires-Dist: js2py
Requires-Dist: scikit-learn
